b2filt/__init__.py
b2filt/errorwriter.py
b2filt/util.py
b2filt-0.2.2.dist-info/LICENSE
b2filt-0.2.2.dist-info/METADATA
b2filt-0.2.2.dist-info/WHEEL
b2filt-0.2.2.dist-info/entry_points.txt
b2filt-0.2.2.dist-info/top_level.txt
b2filt-0.2.2.dist-info/RECORD
